rc_ssl_logtools/__init__.py
rc_ssl_logtools/ssl_importer.py
rc_ssl_logtools/proto/__init__.py
rc_ssl_logtools/proto/messages_robocup_ssl_detection_pb2.py
rc_ssl_logtools/proto/messages_robocup_ssl_geometry_legacy_pb2.py
rc_ssl_logtools/proto/messages_robocup_ssl_geometry_pb2.py
rc_ssl_logtools/proto/messages_robocup_ssl_refbox_log_pb2.py
rc_ssl_logtools/proto/messages_robocup_ssl_wrapper_legacy_pb2.py
rc_ssl_logtools/proto/messages_robocup_ssl_wrapper_pb2.py
rc_ssl_logtools-0.0.4.data/scripts/ssldump
rc_ssl_logtools-0.0.4.dist-info/METADATA
rc_ssl_logtools-0.0.4.dist-info/RECORD
rc_ssl_logtools-0.0.4.dist-info/WHEEL
rc_ssl_logtools-0.0.4.dist-info/top_level.txt
